findmaxima2d/README.md
findmaxima2d/__init__.py
findmaxima2d/cfindmaxima2d.c
findmaxima2d/cfindmaxima2d.cpython-37m-darwin.so
findmaxima2d/cfindmaxima2d.pyx
findmaxima2d/findmaxima2d.py
findmaxima2d/is_within.c
findmaxima2d/is_within.cpython-37m-darwin.so
findmaxima2d/is_within.pyx
findmaxima2d-0.0.28.dist-info/LICENSE
findmaxima2d-0.0.28.dist-info/METADATA
findmaxima2d-0.0.28.dist-info/WHEEL
findmaxima2d-0.0.28.dist-info/top_level.txt
findmaxima2d-0.0.28.dist-info/RECORD
